excelize/__init__.py
excelize/excelize.py
excelize-0.1.0.dist-info/AUTHORS.rst
excelize-0.1.0.dist-info/LICENSE
excelize-0.1.0.dist-info/METADATA
excelize-0.1.0.dist-info/WHEEL
excelize-0.1.0.dist-info/top_level.txt
excelize-0.1.0.dist-info/RECORD
