Metadata-Version: 1.2
Name: excelize
Version: 0.1.0
Summary: Python library for reading and writing Microsoft Excel™ (XLSX) files.
Home-page: https://github.com/TaceyWong/excelize
Author: Tacey Wong
Author-email: xinyong.w@gmail.com
License: BSD license
Keywords: excelize
Platform: UNKNOWN
Classifier: Development Status :: 2 - Pre-Alpha
Classifier: Intended Audience :: Developers
Classifier: License :: OSI Approved :: BSD License
Classifier: Natural Language :: English
Classifier: Programming Language :: Python :: 3
Classifier: Programming Language :: Python :: 3.6
Classifier: Programming Language :: Python :: 3.7
Classifier: Programming Language :: Python :: 3.8
Requires-Python: >=3.6
